setup.py
skip_pygame.py
skip/__init__.py
skip/console_screen.py
skip/pygame_screen.py
skip.egg-info/PKG-INFO
skip.egg-info/SOURCES.txt
skip.egg-info/dependency_links.txt
skip.egg-info/requires.txt
skip.egg-info/top_level.txt