Metadata-Version: 1.0
Name: skip
Version: 0.1.0
Summary: a Python Scratch Interpreter based on Kurt
Home-page: https://github.com/blob8108/skip
Author: Tim Radvan
Author-email: blob8108@gmail.com
License: MIT
Platform: UNKNOWN
Classifier: Programming Language :: Python
